nueveslp1337/__init__.py
nueveslp1337/diskolord.py
nueveslp1337-0.0.1.dist-info/METADATA
nueveslp1337-0.0.1.dist-info/WHEEL
nueveslp1337-0.0.1.dist-info/top_level.txt
nueveslp1337-0.0.1.dist-info/RECORD
