Metadata-Version: 2.4
Name: nueveslp1337
Version: 0.0.1
Summary: module for beautiful color in discord tools
Home-page: 
Author: nueve
Author-email: zakura.int@gmail.com
Classifier: Programming Language :: Python :: 3
Classifier: License :: OSI Approved :: MIT License
Classifier: Operating System :: OS Independent
Dynamic: author
Dynamic: author-email
Dynamic: classifier
Dynamic: description
Dynamic: description-content-type
Dynamic: summary
